gurobi_machinelearning-1.5.5.dist-info/licenses/LICENSE
gurobi_ml/__init__.py
gurobi_ml/_version.py
gurobi_ml/add_predictor.py
gurobi_ml/exceptions.py
gurobi_ml/lightgbm_sklearn_api.py
gurobi_ml/register_user_predictor.py
gurobi_ml/registered_predictors.py
gurobi_ml/xgboost_sklearn_api.py
gurobi_ml/keras/__init__.py
gurobi_ml/keras/keras.py
gurobi_ml/lightgbm/__init__.py
gurobi_ml/lightgbm/lgbm_regressor.py
gurobi_ml/modeling/__init__.py
gurobi_ml/modeling/_submodel.py
gurobi_ml/modeling/_var_utils.py
gurobi_ml/modeling/base_predictor_constr.py
gurobi_ml/modeling/get_convertor.py
gurobi_ml/modeling/decision_tree/__init__.py
gurobi_ml/modeling/decision_tree/decision_tree_model.py
gurobi_ml/modeling/neuralnet/__init__.py
gurobi_ml/modeling/neuralnet/activations.py
gurobi_ml/modeling/neuralnet/layers.py
gurobi_ml/modeling/neuralnet/neural_net.py
gurobi_ml/sklearn/__init__.py
gurobi_ml/sklearn/base_regressions.py
gurobi_ml/sklearn/column_transformer.py
gurobi_ml/sklearn/decision_tree_regressor.py
gurobi_ml/sklearn/gradient_boosting_regressor.py
gurobi_ml/sklearn/linear_regression.py
gurobi_ml/sklearn/logistic_regression.py
gurobi_ml/sklearn/mlpregressor.py
gurobi_ml/sklearn/pipeline.py
gurobi_ml/sklearn/pls_regression.py
gurobi_ml/sklearn/predictors_list.py
gurobi_ml/sklearn/preprocessing.py
gurobi_ml/sklearn/random_forest_regressor.py
gurobi_ml/sklearn/skgetter.py
gurobi_ml/torch/__init__.py
gurobi_ml/torch/sequential.py
gurobi_ml/xgboost/__init__.py
gurobi_ml/xgboost/xgboost_regressor.py
gurobi_machinelearning-1.5.5.dist-info/METADATA
gurobi_machinelearning-1.5.5.dist-info/WHEEL
gurobi_machinelearning-1.5.5.dist-info/top_level.txt
gurobi_machinelearning-1.5.5.dist-info/RECORD
