Metadata-Version: 2.4
Name: gurobi-machinelearning
Version: 1.5.5
Summary: package to insert ML models in Gurobi
Author: Gurobi Optimization LLC
Maintainer: Pierre Bonami
Maintainer-email: bonami@gurobi.com
License: Apache-2.0
Project-URL: Repository, https://github.com/Gurobi/gurobi-machinelearning
Project-URL: Documentation, https://gurobi-optimization-gurobi-machine-learning.readthedocs-hosted.com
Project-URL: Bug Tracker, https://github.com/Gurobi/gurobi-machinelearning/issues
Keywords: mathematical optimization,gurobi,scikit-learn,pytorch,tensorflow,ml
Classifier: Programming Language :: Python :: 3
Classifier: License :: OSI Approved :: Apache Software License
Classifier: Operating System :: OS Independent
Requires-Python: >=3.9
License-File: LICENSE
Requires-Dist: numpy>=1.22.0
Requires-Dist: gurobipy>=10.0.0
Requires-Dist: scipy>=1.9.3
Dynamic: license-file
